LICENSE.txt
README.rst
setup.py
tests/test_cellv2.py
tests/test_commands.py
tests/test_factory.py
tests/test_filters.py
tests/test_processors.py
tests/test_units.py
vhatable/__init__.py
vhatable/cell.py
vhatable/cellv2.py
vhatable/core.py
vhatable/corev2.py
vhatable/demo.py
vhatable/filters.py
vhatable/filtersv2.py
vhatable/processors.py
vhatable/sample.py
vhatable/samplev2.py
vhatable/units.py
vhatable.egg-info/PKG-INFO
vhatable.egg-info/SOURCES.txt
vhatable.egg-info/dependency_links.txt
vhatable.egg-info/entry_points.txt
vhatable.egg-info/requires.txt
vhatable.egg-info/top_level.txt